{
  "arms": [
    "R6",
    "R6s",
    "R5:depthwise"
  ],
  "primary_off": "R6s",
  "eval_inits": 1,
  "epochs": 30,
  "fixes": "real-ablation(R6 vs R6s/depthwise)+eval_inits1+relational-desc+binding-construct",
  "per_seed": [
    {
      "seed": 9,
      "R6": {
        "1": {
          "marginal": {
            "cv": 0.32666666666666666,
            "chance": 0.2,
            "margin": 0.12666666666666665
          },
          "2nd_moment": {
            "cv": 0.3308333333333333,
            "chance": 0.2,
            "margin": 0.1308333333333333
          },
          "coh_eig": {
            "cv": 0.29500000000000004,
            "chance": 0.2,
            "margin": 0.09500000000000003
          },
          "cluster_occ": {
            "cv": 0.2058333333333333,
            "chance": 0.2,
            "margin": 0.0058333333333333015
          },
          "spatial4x4": {
            "cv": 0.35583333333333333,
            "chance": 0.2,
            "margin": 0.15583333333333332
          }
        },
        "2": {
          "marginal": {
            "cv": 0.39666666666666667,
            "chance": 0.2,
            "margin": 0.19666666666666666
          },
          "2nd_moment": {
            "cv": 0.3641666666666667,
            "chance": 0.2,
            "margin": 0.16416666666666668
          },
          "coh_eig": {
            "cv": 0.325,
            "chance": 0.2,
            "margin": 0.125
          },
          "cluster_occ": {
            "cv": 0.2966666666666667,
            "chance": 0.2,
            "margin": 0.09666666666666668
          },
          "spatial4x4": {
            "cv": 0.42666666666666664,
            "chance": 0.2,
            "margin": 0.22666666666666663
          }
        }
      },
      "R6s": {
        "1": {
          "marginal": {
            "cv": 0.31333333333333335,
            "chance": 0.2,
            "margin": 0.11333333333333334
          },
          "2nd_moment": {
            "cv": 0.3725,
            "chance": 0.2,
            "margin": 0.1725
          },
          "coh_eig": {
            "cv": 0.3025,
            "chance": 0.2,
            "margin": 0.10249999999999998
          },
          "cluster_occ": {
            "cv": 0.18583333333333335,
            "chance": 0.2,
            "margin": -0.01416666666666666
          },
          "spatial4x4": {
            "cv": 0.38583333333333336,
            "chance": 0.2,
            "margin": 0.18583333333333335
          }
        },
        "2": {
          "marginal": {
            "cv": 0.4058333333333334,
            "chance": 0.2,
            "margin": 0.20583333333333337
          },
          "2nd_moment": {
            "cv": 0.39249999999999996,
            "chance": 0.2,
            "margin": 0.19249999999999995
          },
          "coh_eig": {
            "cv": 0.41000000000000003,
            "chance": 0.2,
            "margin": 0.21000000000000002
          },
          "cluster_occ": {
            "cv": 0.23333333333333334,
            "chance": 0.2,
            "margin": 0.033333333333333326
          },
          "spatial4x4": {
            "cv": 0.43583333333333335,
            "chance": 0.2,
            "margin": 0.23583333333333334
          }
        }
      },
      "R5:depthwise": {
        "1": {
          "marginal": {
            "cv": 0.26749999999999996,
            "chance": 0.2,
            "margin": 0.06749999999999995
          },
          "2nd_moment": {
            "cv": 0.3225,
            "chance": 0.2,
            "margin": 0.1225
          },
          "coh_eig": {
            "cv": 0.23583333333333334,
            "chance": 0.2,
            "margin": 0.03583333333333333
          },
          "cluster_occ": {
            "cv": 0.19833333333333333,
            "chance": 0.2,
            "margin": -0.0016666666666666774
          },
          "spatial4x4": {
            "cv": 0.32333333333333336,
            "chance": 0.2,
            "margin": 0.12333333333333335
          }
        },
        "2": {
          "marginal": {
            "cv": 0.35500000000000004,
            "chance": 0.2,
            "margin": 0.15500000000000003
          },
          "2nd_moment": {
            "cv": 0.35500000000000004,
            "chance": 0.2,
            "margin": 0.15500000000000003
          },
          "coh_eig": {
            "cv": 0.3491666666666666,
            "chance": 0.2,
            "margin": 0.14916666666666661
          },
          "cluster_occ": {
            "cv": 0.27749999999999997,
            "chance": 0.2,
            "margin": 0.07749999999999996
          },
          "spatial4x4": {
            "cv": 0.3325,
            "chance": 0.2,
            "margin": 0.1325
          }
        }
      }
    },
    {
      "seed": 10,
      "R6": {
        "1": {
          "marginal": {
            "cv": 0.39166666666666666,
            "chance": 0.2,
            "margin": 0.19166666666666665
          },
          "2nd_moment": {
            "cv": 0.4375,
            "chance": 0.2,
            "margin": 0.2375
          },
          "coh_eig": {
            "cv": 0.3875,
            "chance": 0.2,
            "margin": 0.1875
          },
          "cluster_occ": {
            "cv": 0.25083333333333335,
            "chance": 0.2,
            "margin": 0.05083333333333334
          },
          "spatial4x4": {
            "cv": 0.40083333333333326,
            "chance": 0.2,
            "margin": 0.20083333333333325
          }
        },
        "2": {
          "marginal": {
            "cv": 0.3566666666666667,
            "chance": 0.2,
            "margin": 0.15666666666666668
          },
          "2nd_moment": {
            "cv": 0.41916666666666663,
            "chance": 0.2,
            "margin": 0.21916666666666662
          },
          "coh_eig": {
            "cv": 0.39166666666666666,
            "chance": 0.2,
            "margin": 0.19166666666666665
          },
          "cluster_occ": {
            "cv": 0.275,
            "chance": 0.2,
            "margin": 0.07500000000000001
          },
          "spatial4x4": {
            "cv": 0.3875,
            "chance": 0.2,
            "margin": 0.1875
          }
        }
      },
      "R6s": {
        "1": {
          "marginal": {
            "cv": 0.31999999999999995,
            "chance": 0.2,
            "margin": 0.11999999999999994
          },
          "2nd_moment": {
            "cv": 0.30416666666666664,
            "chance": 0.2,
            "margin": 0.10416666666666663
          },
          "coh_eig": {
            "cv": 0.2758333333333333,
            "chance": 0.2,
            "margin": 0.07583333333333331
          },
          "cluster_occ": {
            "cv": 0.2033333333333333,
            "chance": 0.2,
            "margin": 0.0033333333333332993
          },
          "spatial4x4": {
            "cv": 0.3475,
            "chance": 0.2,
            "margin": 0.14749999999999996
          }
        },
        "2": {
          "marginal": {
            "cv": 0.37333333333333335,
            "chance": 0.2,
            "margin": 0.17333333333333334
          },
          "2nd_moment": {
            "cv": 0.3858333333333333,
            "chance": 0.2,
            "margin": 0.1858333333333333
          },
          "coh_eig": {
            "cv": 0.305,
            "chance": 0.2,
            "margin": 0.10499999999999998
          },
          "cluster_occ": {
            "cv": 0.2441666666666667,
            "chance": 0.2,
            "margin": 0.04416666666666669
          },
          "spatial4x4": {
            "cv": 0.37750000000000006,
            "chance": 0.2,
            "margin": 0.17750000000000005
          }
        }
      },
      "R5:depthwise": {
        "1": {
          "marginal": {
            "cv": 0.34833333333333333,
            "chance": 0.2,
            "margin": 0.14833333333333332
          },
          "2nd_moment": {
            "cv": 0.40166666666666667,
            "chance": 0.2,
            "margin": 0.20166666666666666
          },
          "coh_eig": {
            "cv": 0.32,
            "chance": 0.2,
            "margin": 0.12
          },
          "cluster_occ": {
            "cv": 0.20833333333333334,
            "chance": 0.2,
            "margin": 0.008333333333333331
          },
          "spatial4x4": {
            "cv": 0.3725,
            "chance": 0.2,
            "margin": 0.1725
          }
        },
        "2": {
          "marginal": {
            "cv": 0.35333333333333333,
            "chance": 0.2,
            "margin": 0.15333333333333332
          },
          "2nd_moment": {
            "cv": 0.32083333333333336,
            "chance": 0.2,
            "margin": 0.12083333333333335
          },
          "coh_eig": {
            "cv": 0.34416666666666673,
            "chance": 0.2,
            "margin": 0.14416666666666672
          },
          "cluster_occ": {
            "cv": 0.23666666666666664,
            "chance": 0.2,
            "margin": 0.036666666666666625
          },
          "spatial4x4": {
            "cv": 0.3958333333333333,
            "chance": 0.2,
            "margin": 0.1958333333333333
          }
        }
      }
    },
    {
      "seed": 11,
      "R6": {
        "1": {
          "marginal": {
            "cv": 0.42333333333333334,
            "chance": 0.2,
            "margin": 0.22333333333333333
          },
          "2nd_moment": {
            "cv": 0.4258333333333333,
            "chance": 0.2,
            "margin": 0.22583333333333327
          },
          "coh_eig": {
            "cv": 0.39499999999999996,
            "chance": 0.2,
            "margin": 0.19499999999999995
          },
          "cluster_occ": {
            "cv": 0.22000000000000003,
            "chance": 0.2,
            "margin": 0.020000000000000018
          },
          "spatial4x4": {
            "cv": 0.4758333333333333,
            "chance": 0.2,
            "margin": 0.27583333333333326
          }
        },
        "2": {
          "marginal": {
            "cv": 0.4008333333333334,
            "chance": 0.2,
            "margin": 0.20083333333333336
          },
          "2nd_moment": {
            "cv": 0.4541666666666667,
            "chance": 0.2,
            "margin": 0.2541666666666667
          },
          "coh_eig": {
            "cv": 0.37583333333333335,
            "chance": 0.2,
            "margin": 0.17583333333333334
          },
          "cluster_occ": {
            "cv": 0.3341666666666666,
            "chance": 0.2,
            "margin": 0.1341666666666666
          },
          "spatial4x4": {
            "cv": 0.4458333333333333,
            "chance": 0.2,
            "margin": 0.2458333333333333
          }
        }
      },
      "R6s": {
        "1": {
          "marginal": {
            "cv": 0.30166666666666664,
            "chance": 0.2,
            "margin": 0.10166666666666663
          },
          "2nd_moment": {
            "cv": 0.29416666666666663,
            "chance": 0.2,
            "margin": 0.09416666666666662
          },
          "coh_eig": {
            "cv": 0.2733333333333333,
            "chance": 0.2,
            "margin": 0.0733333333333333
          },
          "cluster_occ": {
            "cv": 0.26749999999999996,
            "chance": 0.2,
            "margin": 0.06749999999999995
          },
          "spatial4x4": {
            "cv": 0.3075,
            "chance": 0.2,
            "margin": 0.10749999999999998
          }
        },
        "2": {
          "marginal": {
            "cv": 0.37333333333333335,
            "chance": 0.2,
            "margin": 0.17333333333333334
          },
          "2nd_moment": {
            "cv": 0.38166666666666665,
            "chance": 0.2,
            "margin": 0.18166666666666664
          },
          "coh_eig": {
            "cv": 0.33166666666666667,
            "chance": 0.2,
            "margin": 0.13166666666666665
          },
          "cluster_occ": {
            "cv": 0.19249999999999998,
            "chance": 0.2,
            "margin": -0.007500000000000034
          },
          "spatial4x4": {
            "cv": 0.3916666666666667,
            "chance": 0.2,
            "margin": 0.1916666666666667
          }
        }
      },
      "R5:depthwise": {
        "1": {
          "marginal": {
            "cv": 0.20583333333333337,
            "chance": 0.2,
            "margin": 0.005833333333333357
          },
          "2nd_moment": {
            "cv": 0.21833333333333332,
            "chance": 0.2,
            "margin": 0.018333333333333313
          },
          "coh_eig": {
            "cv": 0.225,
            "chance": 0.2,
            "margin": 0.024999999999999994
          },
          "cluster_occ": {
            "cv": 0.19583333333333333,
            "chance": 0.2,
            "margin": -0.00416666666666668
          },
          "spatial4x4": {
            "cv": 0.22416666666666668,
            "chance": 0.2,
            "margin": 0.02416666666666667
          }
        },
        "2": {
          "marginal": {
            "cv": 0.2,
            "chance": 0.2,
            "margin": 0.0
          },
          "2nd_moment": {
            "cv": 0.2,
            "chance": 0.2,
            "margin": 0.0
          },
          "coh_eig": {
            "cv": 0.2,
            "chance": 0.2,
            "margin": 0.0
          },
          "cluster_occ": {
            "cv": 0.20833333333333331,
            "chance": 0.2,
            "margin": 0.008333333333333304
          },
          "spatial4x4": {
            "cv": 0.21583333333333332,
            "chance": 0.2,
            "margin": 0.01583333333333331
          }
        }
      }
    }
  ],
  "verdict": {
    "call": "CORRECTED-NULL (even with real ablation + eval_inits=1 + relational descriptors on a binding construct, R6 ~ R6s -> synchrony adds no decodable context-channel info)",
    "proceed_hits": [],
    "summary": {
      "R6s": {
        "1": {
          "marginal": {
            "mean_cv_R6": 0.38055555555555554,
            "mean_cv_off": 0.31166666666666665,
            "mean_delta": 0.0688888888888889,
            "p1": 0.125,
            "n_pos": 3,
            "n": 3
          },
          "2nd_moment": {
            "mean_cv_R6": 0.39805555555555555,
            "mean_cv_off": 0.32361111111111107,
            "mean_delta": 0.07444444444444444,
            "p1": 0.25,
            "n_pos": 2,
            "n": 3
          },
          "coh_eig": {
            "mean_cv_R6": 0.3591666666666667,
            "mean_cv_off": 0.2838888888888889,
            "mean_delta": 0.07527777777777779,
            "p1": 0.25,
            "n_pos": 2,
            "n": 3
          },
          "cluster_occ": {
            "mean_cv_R6": 0.2255555555555556,
            "mean_cv_off": 0.21888888888888888,
            "mean_delta": 0.006666666666666691,
            "p1": 0.5,
            "n_pos": 2,
            "n": 3
          },
          "spatial4x4": {
            "mean_cv_R6": 0.41083333333333333,
            "mean_cv_off": 0.3469444444444445,
            "mean_delta": 0.06388888888888884,
            "p1": 0.25,
            "n_pos": 2,
            "n": 3
          }
        },
        "2": {
          "marginal": {
            "mean_cv_R6": 0.38472222222222224,
            "mean_cv_off": 0.3841666666666667,
            "mean_delta": 0.0005555555555555499,
            "p1": 0.5,
            "n_pos": 1,
            "n": 3
          },
          "2nd_moment": {
            "mean_cv_R6": 0.41250000000000003,
            "mean_cv_off": 0.38666666666666666,
            "mean_delta": 0.025833333333333375,
            "p1": 0.25,
            "n_pos": 2,
            "n": 3
          },
          "coh_eig": {
            "mean_cv_R6": 0.3641666666666667,
            "mean_cv_off": 0.34888888888888897,
            "mean_delta": 0.015277777777777779,
            "p1": 0.375,
            "n_pos": 2,
            "n": 3
          },
          "cluster_occ": {
            "mean_cv_R6": 0.30194444444444446,
            "mean_cv_off": 0.22333333333333336,
            "mean_delta": 0.0786111111111111,
            "p1": 0.125,
            "n_pos": 3,
            "n": 3
          },
          "spatial4x4": {
            "mean_cv_R6": 0.42,
            "mean_cv_off": 0.40166666666666667,
            "mean_delta": 0.018333333333333274,
            "p1": 0.25,
            "n_pos": 2,
            "n": 3
          }
        }
      },
      "R5:depthwise": {
        "1": {
          "marginal": {
            "mean_cv_R6": 0.38055555555555554,
            "mean_cv_off": 0.27388888888888885,
            "mean_delta": 0.10666666666666667,
            "p1": 0.125,
            "n_pos": 3,
            "n": 3
          },
          "2nd_moment": {
            "mean_cv_R6": 0.39805555555555555,
            "mean_cv_off": 0.31416666666666665,
            "mean_delta": 0.08388888888888886,
            "p1": 0.125,
            "n_pos": 3,
            "n": 3
          },
          "coh_eig": {
            "mean_cv_R6": 0.3591666666666667,
            "mean_cv_off": 0.2602777777777778,
            "mean_delta": 0.09888888888888887,
            "p1": 0.125,
            "n_pos": 3,
            "n": 3
          },
          "cluster_occ": {
            "mean_cv_R6": 0.2255555555555556,
            "mean_cv_off": 0.20083333333333334,
            "mean_delta": 0.02472222222222223,
            "p1": 0.125,
            "n_pos": 3,
            "n": 3
          },
          "spatial4x4": {
            "mean_cv_R6": 0.41083333333333333,
            "mean_cv_off": 0.30666666666666664,
            "mean_delta": 0.10416666666666662,
            "p1": 0.125,
            "n_pos": 3,
            "n": 3
          }
        },
        "2": {
          "marginal": {
            "mean_cv_R6": 0.38472222222222224,
            "mean_cv_off": 0.3027777777777778,
            "mean_delta": 0.08194444444444444,
            "p1": 0.125,
            "n_pos": 3,
            "n": 3
          },
          "2nd_moment": {
            "mean_cv_R6": 0.41250000000000003,
            "mean_cv_off": 0.2919444444444445,
            "mean_delta": 0.12055555555555554,
            "p1": 0.125,
            "n_pos": 3,
            "n": 3
          },
          "coh_eig": {
            "mean_cv_R6": 0.3641666666666667,
            "mean_cv_off": 0.29777777777777775,
            "mean_delta": 0.06638888888888889,
            "p1": 0.25,
            "n_pos": 2,
            "n": 3
          },
          "cluster_occ": {
            "mean_cv_R6": 0.30194444444444446,
            "mean_cv_off": 0.24083333333333332,
            "mean_delta": 0.06111111111111114,
            "p1": 0.125,
            "n_pos": 3,
            "n": 3
          },
          "spatial4x4": {
            "mean_cv_R6": 0.42,
            "mean_cv_off": 0.3147222222222222,
            "mean_delta": 0.10527777777777776,
            "p1": 0.25,
            "n_pos": 2,
            "n": 3
          }
        }
      }
    }
  }
}